roprokka/__init__.py
roprokka-1.0.2.data/scripts/roprokka
roprokka-1.0.2.dist-info/LICENSE
roprokka-1.0.2.dist-info/METADATA
roprokka-1.0.2.dist-info/WHEEL
roprokka-1.0.2.dist-info/top_level.txt
roprokka-1.0.2.dist-info/RECORD
