Metadata-Version: 2.1
Name: roprokka
Version: 1.0.2
Summary: An add on function to consolidate Prokka output
Home-page: https://github.com/jrhendrix/Ropro
Author: Jo Hendrix
Author-email: jrhendrix36@gmail.com
Classifier: Programming Language :: Python :: 3
Classifier: License :: OSI Approved :: MIT License
Classifier: Operating System :: OS Independent
Requires-Python: >=3.6
License-File: LICENSE
Requires-Dist: pysam
